[{
    "_id": {
        "$oid": "5dc301262aca602e28c63fe8"
    },
    "category": "Fruits",
    "name": "Cherry",
    "price": "15.00",
    "imgloc": "./img/Fruit/cherry.jpeg",
    "sellercompany": "Reliance"
}, {
    "_id": {
        "$oid": "5dc3016f3f2e3d2e28ef5b76"
    },
    "category": "Fruits",
    "name": "Strawberry",
    "price": "15.00",
    "imgloc": "./img/Fruit/strawberry.jpeg",
    "sellercompany": "Reliance"
}, {
    "_id": {
        "$oid": "5dc301843f2e3d2e28ef5b77"
    },
    "category": "Fruits",
    "name": "Banana",
    "price": "15.00",
    "imgloc": "./img/Fruit/banana.jpeg",
    "sellercompany": "Reliance"
}, {
    "_id": {
        "$oid": "5dc308653f2e3d2e28ef5b78"
    },
    "category": "Juice",
    "name": "Strawberry Juice",
    "price": "125.00",
    "imgloc": "./img/Juice/strawberry juice.jpeg",
    "sellercompany": "TATA"
}, {
    "_id": {
        "$oid": "5dc308a83f2e3d2e28ef5b79"
    },
    "category": "Juice",
    "name": "Orange Juice",
    "price": "100.00",
    "imgloc": "./img/Juice/orange juice.jpeg",
    "sellercompany": "Reliance"
}, {
    "_id": {
        "$oid": "5dc308e43f2e3d2e28ef5b7a"
    },
    "category": "Juice",
    "name": "Kiwi Juice",
    "price": "150.00",
    "imgloc": "./img/Juice/kiwi juice.jpeg",
    "sellercompany": "TATA"
}, {
    "_id": {
        "$oid": "5dc308fc3f2e3d2e28ef5b7b"
    },
    "category": "Juice",
    "name": "Apple Juice",
    "price": "90.00",
    "imgloc": "./img/Juice/apple juice.jpeg",
    "sellercompany": "Reliance"
}, {
    "_id": {
        "$oid": "5dc309383f2e3d2e28ef5b7c"
    },
    "category": "Juice",
    "name": "Mango Juice",
    "price": "90.00",
    "imgloc": "./img/Juice/mango juice.jpeg",
    "sellercompany": "TATA"
}, {
    "_id": {
        "$oid": "5dc30b093f2e3d2e28ef5b7d"
    },
    "category": "Vegetable",
    "name": "Brinjal",
    "price": "40.00",
    "imgloc": "./img/Vegetable/brinjal.jpeg",
    "sellercompany": "Reliance"
}, {
    "_id": {
        "$oid": "5dc30bbc3f2e3d2e28ef5b7e"
    },
    "category": "Vegetable",
    "name": "Beans",
    "price": "35.00",
    "imgloc": "./img/Vegetable/beans.jpeg",
    "sellercompany": "TATA"
}, {
    "_id": {
        "$oid": "5dc30bcd3f2e3d2e28ef5b7f"
    },
    "category": "Vegetable",
    "name": "Tomato",
    "price": "50.00",
    "imgloc": "./img/Vegetable/tomato.jpeg",
    "sellercompany": "TATA"
}, {
    "_id": {
        "$oid": "5dc6bd915c7e5e376c4bf2a9"
    },
    "name": "Grape Juice",
    "category": "Juice",
    "price": "120.00",
    "imgloc": "./img/Juice/Grape Juice.jpg",
    "sellercompany": "Reliance",
    "__v": {
        "$numberInt": "0"
    }
}, {
    "_id": {
        "$oid": "5dec7427e92cfe21bcf5f207"
    },
    "category": "Fruits",
    "name": "Kiwi",
    "price": "30.00",
    "imgloc": "./img/Fruit/kiwi.jpeg",
    "sellercompany": "TATA"
}, {
    "_id": {
        "$oid": "5dec74cbe92cfe21bcf5f209"
    },
    "category": "Fruits",
    "name": "Apple",
    "price": "10.00",
    "imgloc": "./img/Fruit/apple.jpeg",
    "sellercompany": "TATA"
}, {
    "_id": {
        "$oid": "5dec75a6e92cfe21bcf5f20b"
    },
    "category": "Fruits",
    "name": "Orange",
    "price": "15.00",
    "imgloc": "./img/Fruit/orange.jpeg",
    "sellercompany": "TATA"
}]